zk_screenshot_maker/__init__.py
zk_screenshot_maker/__main__.py
zk_screenshot_maker/cfg.py
zk_screenshot_maker/drawer.py
zk_screenshot_maker/theme_info.py
zk_screenshot_maker/using.py
zk_screenshot_maker/theme/SourceHanSansCN-Normal.ttf
zk_screenshot_maker/theme/ZhenyanGB.ttf
zk_screenshot_maker/theme/bg_0_2048x2732.png
zk_screenshot_maker/theme/bg_1_2048x2732.png
zk_screenshot_maker/theme/bg_2_2048x2732.png
zk_screenshot_maker/theme/bg_3_2048x2732.png
zk_screenshot_maker/theme/bg_4_2048x2732.png
zk_screenshot_maker/theme/bg_5_2048x2732.png
zk_screenshot_maker/theme/bottom_frame_2048x606.png
zk_screenshot_maker-1.0.5.dist-info/METADATA
zk_screenshot_maker-1.0.5.dist-info/WHEEL
zk_screenshot_maker-1.0.5.dist-info/entry_points.txt
zk_screenshot_maker-1.0.5.dist-info/top_level.txt
zk_screenshot_maker-1.0.5.dist-info/RECORD
